DrawExcel/DrawExcel.py
DrawExcel-1.5.dist-info/LICENSE
DrawExcel-1.5.dist-info/METADATA
DrawExcel-1.5.dist-info/WHEEL
DrawExcel-1.5.dist-info/top_level.txt
DrawExcel-1.5.dist-info/RECORD
