Metadata-Version: 2.1
Name: DrawExcel
Version: 1.5
Summary: Tool that draws VBA structure of your MS Excel file.
Home-page: https://github.com/brochuJP/DrawExcel
Author: Jean-Philippe Brochu
Author-email: jpbrochu99@yahoo.ca
License: MIT
Platform: UNKNOWN
Classifier: License :: OSI Approved :: MIT License
Classifier: Programming Language :: Python :: 3
Classifier: Programming Language :: Python :: 3.8
Requires-Dist: pandas
Requires-Dist: pywin32
Requires-Dist: graphviz
